pydantic_azure_keyvault_secrets_types/__init__.py
pydantic_azure_keyvault_secrets_types/key_vault_reference.py
pydantic_azure_keyvault_secrets_types-0.1.1.dist-info/LICENSE
pydantic_azure_keyvault_secrets_types-0.1.1.dist-info/METADATA
pydantic_azure_keyvault_secrets_types-0.1.1.dist-info/WHEEL
pydantic_azure_keyvault_secrets_types-0.1.1.dist-info/RECORD
