Metadata-Version: 2.1
Name: pydantic-azure-keyvault-secrets-types
Version: 0.1.1
Summary: Pydantic Azure Key Vault types
Home-page: https://github.com/ScripTerasu/pydantic-azure-keyvault-secrets-types
License: GPL-3.0-only
Author: Sebastian Almendra
Author-email: script.seba@gmail.com
Requires-Python: >=3.11,<4.0
Classifier: License :: OSI Approved :: GNU General Public License v3 (GPLv3)
Classifier: Programming Language :: Python :: 3
Classifier: Programming Language :: Python :: 3.11
Requires-Dist: azure-identity (>=1.13.0,<2.0.0)
Requires-Dist: azure-keyvault-secrets (>=4.7.0,<5.0.0)
Requires-Dist: pydantic (>=2.1.1,<3.0.0)
Project-URL: Repository, https://github.com/ScripTerasu/pydantic-azure-keyvault-secrets-types
